vro_package_diff/__init__.py
vro_package_diff/__main__.py
vro_package_diff/config.py
vro_package_diff/vro_element.py
vro_package_diff-2.2.2.dist-info/AUTHORS.rst
vro_package_diff-2.2.2.dist-info/LICENSE.md
vro_package_diff-2.2.2.dist-info/METADATA
vro_package_diff-2.2.2.dist-info/WHEEL
vro_package_diff-2.2.2.dist-info/entry_points.txt
vro_package_diff-2.2.2.dist-info/top_level.txt
vro_package_diff-2.2.2.dist-info/RECORD
