Metadata-Version: 2.1
Name: vro-package-diff
Version: 2.2.2
Summary: A diff tool for VMware vRealize Orchestrator packages files
Home-page: https://github.com/lrivallain/vro_package_diff
Author: Ludovic Rivallain
Author-email: ludovic.rivallain@gmail.com
License: UNKNOWN
Platform: UNKNOWN
Classifier: Programming Language :: Python :: 3.5
Classifier: Programming Language :: Python :: 3.6
Classifier: Programming Language :: Python :: 3.6
Classifier: Programming Language :: Python :: 3.7
Classifier: Programming Language :: Python :: 3.8
Classifier: Programming Language :: Python :: 3.9
Classifier: Operating System :: MacOS :: MacOS X
Classifier: Operating System :: Microsoft :: Windows
Classifier: Operating System :: Unix
Classifier: Operating System :: POSIX :: Linux
Classifier: License :: OSI Approved :: MIT License
Classifier: Environment :: Console
Requires-Python: >=3.5
Requires-Dist: terminaltables
Requires-Dist: colored
Requires-Dist: click
Requires-Dist: packaging
